{
  "name": "Weapon",
  "rolls": [
    {
      "name": "aspect",
      "options": [
        "Golden",
        "Quicksilver",
        "Ultraviolet",
        "Crystal",
        "Nomad",
        "Black",
        "Ancient",
        "Bone",
        "Parasitic",
        "Fungal",
        "Ritual",
        "Biomechanical",
        "Sacred",
        "Blasphemous",
        "Venomous",
        "Obsidian",
        "Bronze",
        "Jewelled",
        "Plasma",
        "Translucent"
      ]
    },
    {
      "name": "Form",
      "options": [
        "Knife",
        "Flail",
        "Whip",
        "Axe",
        "Club",
        "Sling",
        "Rapier",
        "Pistol",
        "Spear",
        "Shortbow",
        "Halberd",
        "Rifle",
        "Musket",
        "Shotgun",
        "Crossbow",
        "Sword",
        "Revolver",
        "Laser",
        "Spore Thrower",
        "Railgun"
      ]
    },
    {
      "name": "damage",
      "options": [
        "Light(1 Slot, d6 damage)",
        "Light(1 Slot, d6 damage)",
        "Light(1 Slot, d6 damage)",
        "Light(1 Slot, d6 damage)",
        "Light(1 Slot, d6 damage)",
        "Light(1 Slot, d6 damage)",
        "Light(1 Slot, d6 damage)",
        "Light(1 Slot, d6 damage)",
        "Light(1 Slot, d6 damage)",
        "Light(1 Slot, d6 damage)",
        "Medium (2 slots, d8 damage)",
        "Medium (2 slots, d8 damage)",
        "Medium (2 slots, d8 damage)",
        "Medium (2 slots, d8 damage)",
        "Medium (2 slots, d8 damage)",
        "Medium (2 slots, d8 damage)",
        "Medium (2 slots, d8 damage)",
        "Medium (2 slots, d8 damage)",
        "Heavy (3 slots, d10 damage)",
        "Heavy (3 slots, d10 damage)"
      ]
    }
  ]
}
